\hypertarget{instructions_8h}{}\section{instructions.\+h File Reference}
\label{instructions_8h}\index{instructions.\+h@{instructions.\+h}}
{\ttfamily \#include $<$stdint.\+h$>$}\\*
{\ttfamily \#include \char`\"{}frame.\+h\char`\"{}}\\*
Include dependency graph for instructions.\+h\+:
\nopagebreak
\begin{figure}[H]
\begin{center}
\leavevmode
\includegraphics[width=258pt]{instructions_8h__incl}
\end{center}
\end{figure}
This graph shows which files directly or indirectly include this file\+:
\nopagebreak
\begin{figure}[H]
\begin{center}
\leavevmode
\includegraphics[width=333pt]{instructions_8h__dep__incl}
\end{center}
\end{figure}
\subsection*{Classes}
\begin{DoxyCompactItemize}
\item 
struct \hyperlink{structop__code}{op\+\_\+code}
\begin{DoxyCompactList}\small\item\em Estrutura de dados para facilitar o acesso ao \hyperlink{structop__code}{op\+\_\+code} das instruções durante a execução do interpretador. \end{DoxyCompactList}\end{DoxyCompactItemize}
\subsection*{Enumerations}
\begin{DoxyCompactItemize}
\item 
enum \{ \\*
\hyperlink{instructions_8h_a06fc87d81c62e9abb8790b6e5713c55ba6a8db248e0e6f06a8926e7e9603cd5e9}{newarray} = 188, 
\hyperlink{instructions_8h_a06fc87d81c62e9abb8790b6e5713c55ba1792b72c510eacc6406c3ec6fa29038a}{anewarray} = 189, 
\hyperlink{instructions_8h_a06fc87d81c62e9abb8790b6e5713c55ba1df6aaf4e9442d8b1272e6932537327a}{multianewarray} = 197, 
\hyperlink{instructions_8h_a06fc87d81c62e9abb8790b6e5713c55ba26ac73daf5f262390a6ba1443d0c720a}{checkcast} = 192, 
\\*
\hyperlink{instructions_8h_a06fc87d81c62e9abb8790b6e5713c55ba083d62b5bb07a34ebda72f50d32d7840}{getfield} = 180, 
\hyperlink{instructions_8h_a06fc87d81c62e9abb8790b6e5713c55bae76da9857e6b2a5e6d6b8ef690d333eb}{getstatic} = 178, 
\hyperlink{instructions_8h_a06fc87d81c62e9abb8790b6e5713c55ba7d50404eedc23ede3ebcb1b51b501842}{instanceofg} = 193, 
\hyperlink{instructions_8h_a06fc87d81c62e9abb8790b6e5713c55ba399e79d2b5fa88ee31064d00203b09fe}{invokedynamic} = 186, 
\\*
\hyperlink{instructions_8h_a06fc87d81c62e9abb8790b6e5713c55ba80174b008f2cd5fee3911076ae81e228}{invokeinterface} = 185, 
\hyperlink{instructions_8h_a06fc87d81c62e9abb8790b6e5713c55ba808231aae996fd71a149fff725642f98}{invokespecial} = 183, 
\hyperlink{instructions_8h_a06fc87d81c62e9abb8790b6e5713c55ba612d2d6b9b5c095695a1ebcc9f591bdc}{invokestatic} = 184, 
\hyperlink{instructions_8h_a06fc87d81c62e9abb8790b6e5713c55ba2583d540fcc9e3a51e4b940b735a9284}{invokevirtual} = 182, 
\\*
\hyperlink{instructions_8h_a06fc87d81c62e9abb8790b6e5713c55ba699d54d79640467f9c1e1e31651dd0ed}{ldc} = 18, 
\hyperlink{instructions_8h_a06fc87d81c62e9abb8790b6e5713c55ba2af3cf615623a5234960a653f0a291a7}{ldc\+\_\+w} = 19, 
\hyperlink{instructions_8h_a06fc87d81c62e9abb8790b6e5713c55bafa08e10b0acf38f073bdbdb9867d75c7}{ldc2\+\_\+w} = 20, 
\hyperlink{instructions_8h_a06fc87d81c62e9abb8790b6e5713c55baec34b0b90541576a22697631105dc847}{N\+EW} = 187, 
\\*
\hyperlink{instructions_8h_a06fc87d81c62e9abb8790b6e5713c55bad07a04c305298b3e39f8a4cf0744fb8c}{putfield} = 181, 
\hyperlink{instructions_8h_a06fc87d81c62e9abb8790b6e5713c55ba4224c3934fbb6ba8362e3eb2395c7ff9}{putstatic} = 179, 
\hyperlink{instructions_8h_a06fc87d81c62e9abb8790b6e5713c55ba7287fd9f74eaf3ffc93fffdf54de9165}{ifeq} = 153, 
\hyperlink{instructions_8h_a06fc87d81c62e9abb8790b6e5713c55ba26cdd5fa86326c323b3356e83d76c26d}{ifne} = 154, 
\\*
\hyperlink{instructions_8h_a06fc87d81c62e9abb8790b6e5713c55ba7ee66b7c0b721760377485b141d21f06}{iflt} = 155, 
\hyperlink{instructions_8h_a06fc87d81c62e9abb8790b6e5713c55ba3d404df3e915c997b76d82ac2816f69c}{ifge} = 156, 
\hyperlink{instructions_8h_a06fc87d81c62e9abb8790b6e5713c55baffc34242675922d04b7964ce5b135ee8}{ifgt} = 157, 
\hyperlink{instructions_8h_a06fc87d81c62e9abb8790b6e5713c55ba58dd06bc48e0372be8154ced5fa7c141}{ifle} = 158, 
\\*
\hyperlink{instructions_8h_a06fc87d81c62e9abb8790b6e5713c55ba8288bab3f7390a6cb96318d5c469af8e}{if\+\_\+icmpeq} = 159, 
\hyperlink{instructions_8h_a06fc87d81c62e9abb8790b6e5713c55bad5689e426d58a1c604f824b41814c946}{if\+\_\+icmpne} = 160, 
\hyperlink{instructions_8h_a06fc87d81c62e9abb8790b6e5713c55ba9e3003a006dae3c159e96e0cef58217f}{if\+\_\+icmplt} = 161, 
\hyperlink{instructions_8h_a06fc87d81c62e9abb8790b6e5713c55ba5a086e5c3a3019f69302c4b689a66e95}{if\+\_\+icmpge} = 162, 
\\*
\hyperlink{instructions_8h_a06fc87d81c62e9abb8790b6e5713c55ba5c076edab23d366c19ed40aa38a8fb36}{if\+\_\+icmpgt} = 163, 
\hyperlink{instructions_8h_a06fc87d81c62e9abb8790b6e5713c55ba67d553038afb13dde870deebe0ebdcc3}{if\+\_\+icmple} = 164, 
\hyperlink{instructions_8h_a06fc87d81c62e9abb8790b6e5713c55ba39d950d0f27c4e393b971249aa454b03}{if\+\_\+acmpeq} = 165, 
\hyperlink{instructions_8h_a06fc87d81c62e9abb8790b6e5713c55ba6881f24a67e9aef16b7446bd20f1e98f}{if\+\_\+acmpne} = 166, 
\\*
\hyperlink{instructions_8h_a06fc87d81c62e9abb8790b6e5713c55badf1256e4198172eedfbf12c770d11589}{G\+O\+TO} = 167, 
\hyperlink{instructions_8h_a06fc87d81c62e9abb8790b6e5713c55ba924f50ccafd39193f6751e8b61aef568}{jsr} = 168, 
\hyperlink{instructions_8h_a06fc87d81c62e9abb8790b6e5713c55babd6ddbe3310f6703b36fae4f5a26444f}{ifnonnull} = 199, 
\hyperlink{instructions_8h_a06fc87d81c62e9abb8790b6e5713c55badd6d42007d139025320be3763128aff0}{ifnull} = 198, 
\\*
\hyperlink{instructions_8h_a06fc87d81c62e9abb8790b6e5713c55ba083cba804dff6d007aae654e5b9ef655}{aload} = 25, 
\hyperlink{instructions_8h_a06fc87d81c62e9abb8790b6e5713c55ba73a8344343fd12fb6074b6c8d7564fb1}{aload\+\_\+0} = 42, 
\hyperlink{instructions_8h_a06fc87d81c62e9abb8790b6e5713c55bac3a421ab835d4a2b59f8892f79374284}{aload\+\_\+1} = 43, 
\hyperlink{instructions_8h_a06fc87d81c62e9abb8790b6e5713c55bace3ae920ba39fd1ca14c32927b96bef9}{aload\+\_\+2} = 44, 
\\*
\hyperlink{instructions_8h_a06fc87d81c62e9abb8790b6e5713c55ba2e3b02b418d4895ba8a60e911a029eef}{aload\+\_\+3} = 45, 
\hyperlink{instructions_8h_a06fc87d81c62e9abb8790b6e5713c55badc18648a3db2995e563636a41ad36340}{areturn} = 176, 
\hyperlink{instructions_8h_a06fc87d81c62e9abb8790b6e5713c55ba9a97fb20f5ff36205d94c72df2e62dde}{return\+\_\+original} = 177, 
\hyperlink{instructions_8h_a06fc87d81c62e9abb8790b6e5713c55bae7b0ecf96d2bf1ef455ba9488697c85a}{tableswitch} = 170, 
\\*
\hyperlink{instructions_8h_a06fc87d81c62e9abb8790b6e5713c55bacc321be87baf3cf4b6e0d4b569776156}{lookupswitch} = 171, 
\hyperlink{instructions_8h_a06fc87d81c62e9abb8790b6e5713c55bacf3cc7b9218abdf037d624446b916f67}{wide} = 196, 
\hyperlink{instructions_8h_a06fc87d81c62e9abb8790b6e5713c55ba947df06f627174c299830f76cf19a3c7}{iinc} = 132, 
\hyperlink{instructions_8h_a06fc87d81c62e9abb8790b6e5713c55bafd6c7d5aac2787536813938ae70e9f73}{bipush} = 0x10
 \}\begin{DoxyCompactList}\small\item\em Enum com informações dos opcodes da \hyperlink{structJVM}{J\+VM}. \end{DoxyCompactList}
\end{DoxyCompactItemize}
\subsection*{Functions}
\begin{DoxyCompactItemize}
\item 
void \hyperlink{instructions_8h_afc6e90df89f862010ce7c75d0663ea08}{initialize\+\_\+op\+\_\+codes} ()
\end{DoxyCompactItemize}
\subsection*{Variables}
\begin{DoxyCompactItemize}
\item 
\hyperlink{structop__code}{op\+\_\+code} \hyperlink{instructions_8h_a7037db4717b2292017d30ccec8c29b64}{op\+\_\+codes\+\_\+array} \mbox{[}300\mbox{]}
\item 
enum  \{ ... \}  \hyperlink{instructions_8h_ad80be7537d54389cd2647bb57b4cbf35}{instructions}
\begin{DoxyCompactList}\small\item\em Enum com informações dos opcodes da \hyperlink{structJVM}{J\+VM}. \end{DoxyCompactList}\end{DoxyCompactItemize}


\subsection{Enumeration Type Documentation}
\subsubsection[{\texorpdfstring{anonymous enum}{anonymous enum}}]{\setlength{\rightskip}{0pt plus 5cm}anonymous enum}\hypertarget{instructions_8h_a06fc87d81c62e9abb8790b6e5713c55b}{}\label{instructions_8h_a06fc87d81c62e9abb8790b6e5713c55b}


Enum com informações dos opcodes da \hyperlink{structJVM}{J\+VM}. 

\begin{Desc}
\item[Enumerator]\par
\begin{description}
\index{newarray@{newarray}!instructions.\+h@{instructions.\+h}}\index{instructions.\+h@{instructions.\+h}!newarray@{newarray}}\item[{\em 
newarray\hypertarget{instructions_8h_a06fc87d81c62e9abb8790b6e5713c55ba6a8db248e0e6f06a8926e7e9603cd5e9}{}\label{instructions_8h_a06fc87d81c62e9abb8790b6e5713c55ba6a8db248e0e6f06a8926e7e9603cd5e9}
}]\index{anewarray@{anewarray}!instructions.\+h@{instructions.\+h}}\index{instructions.\+h@{instructions.\+h}!anewarray@{anewarray}}\item[{\em 
anewarray\hypertarget{instructions_8h_a06fc87d81c62e9abb8790b6e5713c55ba1792b72c510eacc6406c3ec6fa29038a}{}\label{instructions_8h_a06fc87d81c62e9abb8790b6e5713c55ba1792b72c510eacc6406c3ec6fa29038a}
}]\index{multianewarray@{multianewarray}!instructions.\+h@{instructions.\+h}}\index{instructions.\+h@{instructions.\+h}!multianewarray@{multianewarray}}\item[{\em 
multianewarray\hypertarget{instructions_8h_a06fc87d81c62e9abb8790b6e5713c55ba1df6aaf4e9442d8b1272e6932537327a}{}\label{instructions_8h_a06fc87d81c62e9abb8790b6e5713c55ba1df6aaf4e9442d8b1272e6932537327a}
}]\index{checkcast@{checkcast}!instructions.\+h@{instructions.\+h}}\index{instructions.\+h@{instructions.\+h}!checkcast@{checkcast}}\item[{\em 
checkcast\hypertarget{instructions_8h_a06fc87d81c62e9abb8790b6e5713c55ba26ac73daf5f262390a6ba1443d0c720a}{}\label{instructions_8h_a06fc87d81c62e9abb8790b6e5713c55ba26ac73daf5f262390a6ba1443d0c720a}
}]\index{getfield@{getfield}!instructions.\+h@{instructions.\+h}}\index{instructions.\+h@{instructions.\+h}!getfield@{getfield}}\item[{\em 
getfield\hypertarget{instructions_8h_a06fc87d81c62e9abb8790b6e5713c55ba083d62b5bb07a34ebda72f50d32d7840}{}\label{instructions_8h_a06fc87d81c62e9abb8790b6e5713c55ba083d62b5bb07a34ebda72f50d32d7840}
}]\index{getstatic@{getstatic}!instructions.\+h@{instructions.\+h}}\index{instructions.\+h@{instructions.\+h}!getstatic@{getstatic}}\item[{\em 
getstatic\hypertarget{instructions_8h_a06fc87d81c62e9abb8790b6e5713c55bae76da9857e6b2a5e6d6b8ef690d333eb}{}\label{instructions_8h_a06fc87d81c62e9abb8790b6e5713c55bae76da9857e6b2a5e6d6b8ef690d333eb}
}]\index{instanceofg@{instanceofg}!instructions.\+h@{instructions.\+h}}\index{instructions.\+h@{instructions.\+h}!instanceofg@{instanceofg}}\item[{\em 
instanceofg\hypertarget{instructions_8h_a06fc87d81c62e9abb8790b6e5713c55ba7d50404eedc23ede3ebcb1b51b501842}{}\label{instructions_8h_a06fc87d81c62e9abb8790b6e5713c55ba7d50404eedc23ede3ebcb1b51b501842}
}]\index{invokedynamic@{invokedynamic}!instructions.\+h@{instructions.\+h}}\index{instructions.\+h@{instructions.\+h}!invokedynamic@{invokedynamic}}\item[{\em 
invokedynamic\hypertarget{instructions_8h_a06fc87d81c62e9abb8790b6e5713c55ba399e79d2b5fa88ee31064d00203b09fe}{}\label{instructions_8h_a06fc87d81c62e9abb8790b6e5713c55ba399e79d2b5fa88ee31064d00203b09fe}
}]\index{invokeinterface@{invokeinterface}!instructions.\+h@{instructions.\+h}}\index{instructions.\+h@{instructions.\+h}!invokeinterface@{invokeinterface}}\item[{\em 
invokeinterface\hypertarget{instructions_8h_a06fc87d81c62e9abb8790b6e5713c55ba80174b008f2cd5fee3911076ae81e228}{}\label{instructions_8h_a06fc87d81c62e9abb8790b6e5713c55ba80174b008f2cd5fee3911076ae81e228}
}]\index{invokespecial@{invokespecial}!instructions.\+h@{instructions.\+h}}\index{instructions.\+h@{instructions.\+h}!invokespecial@{invokespecial}}\item[{\em 
invokespecial\hypertarget{instructions_8h_a06fc87d81c62e9abb8790b6e5713c55ba808231aae996fd71a149fff725642f98}{}\label{instructions_8h_a06fc87d81c62e9abb8790b6e5713c55ba808231aae996fd71a149fff725642f98}
}]\index{invokestatic@{invokestatic}!instructions.\+h@{instructions.\+h}}\index{instructions.\+h@{instructions.\+h}!invokestatic@{invokestatic}}\item[{\em 
invokestatic\hypertarget{instructions_8h_a06fc87d81c62e9abb8790b6e5713c55ba612d2d6b9b5c095695a1ebcc9f591bdc}{}\label{instructions_8h_a06fc87d81c62e9abb8790b6e5713c55ba612d2d6b9b5c095695a1ebcc9f591bdc}
}]\index{invokevirtual@{invokevirtual}!instructions.\+h@{instructions.\+h}}\index{instructions.\+h@{instructions.\+h}!invokevirtual@{invokevirtual}}\item[{\em 
invokevirtual\hypertarget{instructions_8h_a06fc87d81c62e9abb8790b6e5713c55ba2583d540fcc9e3a51e4b940b735a9284}{}\label{instructions_8h_a06fc87d81c62e9abb8790b6e5713c55ba2583d540fcc9e3a51e4b940b735a9284}
}]\index{ldc@{ldc}!instructions.\+h@{instructions.\+h}}\index{instructions.\+h@{instructions.\+h}!ldc@{ldc}}\item[{\em 
ldc\hypertarget{instructions_8h_a06fc87d81c62e9abb8790b6e5713c55ba699d54d79640467f9c1e1e31651dd0ed}{}\label{instructions_8h_a06fc87d81c62e9abb8790b6e5713c55ba699d54d79640467f9c1e1e31651dd0ed}
}]\index{ldc\+\_\+w@{ldc\+\_\+w}!instructions.\+h@{instructions.\+h}}\index{instructions.\+h@{instructions.\+h}!ldc\+\_\+w@{ldc\+\_\+w}}\item[{\em 
ldc\+\_\+w\hypertarget{instructions_8h_a06fc87d81c62e9abb8790b6e5713c55ba2af3cf615623a5234960a653f0a291a7}{}\label{instructions_8h_a06fc87d81c62e9abb8790b6e5713c55ba2af3cf615623a5234960a653f0a291a7}
}]\index{ldc2\+\_\+w@{ldc2\+\_\+w}!instructions.\+h@{instructions.\+h}}\index{instructions.\+h@{instructions.\+h}!ldc2\+\_\+w@{ldc2\+\_\+w}}\item[{\em 
ldc2\+\_\+w\hypertarget{instructions_8h_a06fc87d81c62e9abb8790b6e5713c55bafa08e10b0acf38f073bdbdb9867d75c7}{}\label{instructions_8h_a06fc87d81c62e9abb8790b6e5713c55bafa08e10b0acf38f073bdbdb9867d75c7}
}]\index{N\+EW@{N\+EW}!instructions.\+h@{instructions.\+h}}\index{instructions.\+h@{instructions.\+h}!N\+EW@{N\+EW}}\item[{\em 
N\+EW\hypertarget{instructions_8h_a06fc87d81c62e9abb8790b6e5713c55baec34b0b90541576a22697631105dc847}{}\label{instructions_8h_a06fc87d81c62e9abb8790b6e5713c55baec34b0b90541576a22697631105dc847}
}]\index{putfield@{putfield}!instructions.\+h@{instructions.\+h}}\index{instructions.\+h@{instructions.\+h}!putfield@{putfield}}\item[{\em 
putfield\hypertarget{instructions_8h_a06fc87d81c62e9abb8790b6e5713c55bad07a04c305298b3e39f8a4cf0744fb8c}{}\label{instructions_8h_a06fc87d81c62e9abb8790b6e5713c55bad07a04c305298b3e39f8a4cf0744fb8c}
}]\index{putstatic@{putstatic}!instructions.\+h@{instructions.\+h}}\index{instructions.\+h@{instructions.\+h}!putstatic@{putstatic}}\item[{\em 
putstatic\hypertarget{instructions_8h_a06fc87d81c62e9abb8790b6e5713c55ba4224c3934fbb6ba8362e3eb2395c7ff9}{}\label{instructions_8h_a06fc87d81c62e9abb8790b6e5713c55ba4224c3934fbb6ba8362e3eb2395c7ff9}
}]\index{ifeq@{ifeq}!instructions.\+h@{instructions.\+h}}\index{instructions.\+h@{instructions.\+h}!ifeq@{ifeq}}\item[{\em 
ifeq\hypertarget{instructions_8h_a06fc87d81c62e9abb8790b6e5713c55ba7287fd9f74eaf3ffc93fffdf54de9165}{}\label{instructions_8h_a06fc87d81c62e9abb8790b6e5713c55ba7287fd9f74eaf3ffc93fffdf54de9165}
}]\index{ifne@{ifne}!instructions.\+h@{instructions.\+h}}\index{instructions.\+h@{instructions.\+h}!ifne@{ifne}}\item[{\em 
ifne\hypertarget{instructions_8h_a06fc87d81c62e9abb8790b6e5713c55ba26cdd5fa86326c323b3356e83d76c26d}{}\label{instructions_8h_a06fc87d81c62e9abb8790b6e5713c55ba26cdd5fa86326c323b3356e83d76c26d}
}]\index{iflt@{iflt}!instructions.\+h@{instructions.\+h}}\index{instructions.\+h@{instructions.\+h}!iflt@{iflt}}\item[{\em 
iflt\hypertarget{instructions_8h_a06fc87d81c62e9abb8790b6e5713c55ba7ee66b7c0b721760377485b141d21f06}{}\label{instructions_8h_a06fc87d81c62e9abb8790b6e5713c55ba7ee66b7c0b721760377485b141d21f06}
}]\index{ifge@{ifge}!instructions.\+h@{instructions.\+h}}\index{instructions.\+h@{instructions.\+h}!ifge@{ifge}}\item[{\em 
ifge\hypertarget{instructions_8h_a06fc87d81c62e9abb8790b6e5713c55ba3d404df3e915c997b76d82ac2816f69c}{}\label{instructions_8h_a06fc87d81c62e9abb8790b6e5713c55ba3d404df3e915c997b76d82ac2816f69c}
}]\index{ifgt@{ifgt}!instructions.\+h@{instructions.\+h}}\index{instructions.\+h@{instructions.\+h}!ifgt@{ifgt}}\item[{\em 
ifgt\hypertarget{instructions_8h_a06fc87d81c62e9abb8790b6e5713c55baffc34242675922d04b7964ce5b135ee8}{}\label{instructions_8h_a06fc87d81c62e9abb8790b6e5713c55baffc34242675922d04b7964ce5b135ee8}
}]\index{ifle@{ifle}!instructions.\+h@{instructions.\+h}}\index{instructions.\+h@{instructions.\+h}!ifle@{ifle}}\item[{\em 
ifle\hypertarget{instructions_8h_a06fc87d81c62e9abb8790b6e5713c55ba58dd06bc48e0372be8154ced5fa7c141}{}\label{instructions_8h_a06fc87d81c62e9abb8790b6e5713c55ba58dd06bc48e0372be8154ced5fa7c141}
}]\index{if\+\_\+icmpeq@{if\+\_\+icmpeq}!instructions.\+h@{instructions.\+h}}\index{instructions.\+h@{instructions.\+h}!if\+\_\+icmpeq@{if\+\_\+icmpeq}}\item[{\em 
if\+\_\+icmpeq\hypertarget{instructions_8h_a06fc87d81c62e9abb8790b6e5713c55ba8288bab3f7390a6cb96318d5c469af8e}{}\label{instructions_8h_a06fc87d81c62e9abb8790b6e5713c55ba8288bab3f7390a6cb96318d5c469af8e}
}]\index{if\+\_\+icmpne@{if\+\_\+icmpne}!instructions.\+h@{instructions.\+h}}\index{instructions.\+h@{instructions.\+h}!if\+\_\+icmpne@{if\+\_\+icmpne}}\item[{\em 
if\+\_\+icmpne\hypertarget{instructions_8h_a06fc87d81c62e9abb8790b6e5713c55bad5689e426d58a1c604f824b41814c946}{}\label{instructions_8h_a06fc87d81c62e9abb8790b6e5713c55bad5689e426d58a1c604f824b41814c946}
}]\index{if\+\_\+icmplt@{if\+\_\+icmplt}!instructions.\+h@{instructions.\+h}}\index{instructions.\+h@{instructions.\+h}!if\+\_\+icmplt@{if\+\_\+icmplt}}\item[{\em 
if\+\_\+icmplt\hypertarget{instructions_8h_a06fc87d81c62e9abb8790b6e5713c55ba9e3003a006dae3c159e96e0cef58217f}{}\label{instructions_8h_a06fc87d81c62e9abb8790b6e5713c55ba9e3003a006dae3c159e96e0cef58217f}
}]\index{if\+\_\+icmpge@{if\+\_\+icmpge}!instructions.\+h@{instructions.\+h}}\index{instructions.\+h@{instructions.\+h}!if\+\_\+icmpge@{if\+\_\+icmpge}}\item[{\em 
if\+\_\+icmpge\hypertarget{instructions_8h_a06fc87d81c62e9abb8790b6e5713c55ba5a086e5c3a3019f69302c4b689a66e95}{}\label{instructions_8h_a06fc87d81c62e9abb8790b6e5713c55ba5a086e5c3a3019f69302c4b689a66e95}
}]\index{if\+\_\+icmpgt@{if\+\_\+icmpgt}!instructions.\+h@{instructions.\+h}}\index{instructions.\+h@{instructions.\+h}!if\+\_\+icmpgt@{if\+\_\+icmpgt}}\item[{\em 
if\+\_\+icmpgt\hypertarget{instructions_8h_a06fc87d81c62e9abb8790b6e5713c55ba5c076edab23d366c19ed40aa38a8fb36}{}\label{instructions_8h_a06fc87d81c62e9abb8790b6e5713c55ba5c076edab23d366c19ed40aa38a8fb36}
}]\index{if\+\_\+icmple@{if\+\_\+icmple}!instructions.\+h@{instructions.\+h}}\index{instructions.\+h@{instructions.\+h}!if\+\_\+icmple@{if\+\_\+icmple}}\item[{\em 
if\+\_\+icmple\hypertarget{instructions_8h_a06fc87d81c62e9abb8790b6e5713c55ba67d553038afb13dde870deebe0ebdcc3}{}\label{instructions_8h_a06fc87d81c62e9abb8790b6e5713c55ba67d553038afb13dde870deebe0ebdcc3}
}]\index{if\+\_\+acmpeq@{if\+\_\+acmpeq}!instructions.\+h@{instructions.\+h}}\index{instructions.\+h@{instructions.\+h}!if\+\_\+acmpeq@{if\+\_\+acmpeq}}\item[{\em 
if\+\_\+acmpeq\hypertarget{instructions_8h_a06fc87d81c62e9abb8790b6e5713c55ba39d950d0f27c4e393b971249aa454b03}{}\label{instructions_8h_a06fc87d81c62e9abb8790b6e5713c55ba39d950d0f27c4e393b971249aa454b03}
}]\index{if\+\_\+acmpne@{if\+\_\+acmpne}!instructions.\+h@{instructions.\+h}}\index{instructions.\+h@{instructions.\+h}!if\+\_\+acmpne@{if\+\_\+acmpne}}\item[{\em 
if\+\_\+acmpne\hypertarget{instructions_8h_a06fc87d81c62e9abb8790b6e5713c55ba6881f24a67e9aef16b7446bd20f1e98f}{}\label{instructions_8h_a06fc87d81c62e9abb8790b6e5713c55ba6881f24a67e9aef16b7446bd20f1e98f}
}]\index{G\+O\+TO@{G\+O\+TO}!instructions.\+h@{instructions.\+h}}\index{instructions.\+h@{instructions.\+h}!G\+O\+TO@{G\+O\+TO}}\item[{\em 
G\+O\+TO\hypertarget{instructions_8h_a06fc87d81c62e9abb8790b6e5713c55badf1256e4198172eedfbf12c770d11589}{}\label{instructions_8h_a06fc87d81c62e9abb8790b6e5713c55badf1256e4198172eedfbf12c770d11589}
}]\index{jsr@{jsr}!instructions.\+h@{instructions.\+h}}\index{instructions.\+h@{instructions.\+h}!jsr@{jsr}}\item[{\em 
jsr\hypertarget{instructions_8h_a06fc87d81c62e9abb8790b6e5713c55ba924f50ccafd39193f6751e8b61aef568}{}\label{instructions_8h_a06fc87d81c62e9abb8790b6e5713c55ba924f50ccafd39193f6751e8b61aef568}
}]\index{ifnonnull@{ifnonnull}!instructions.\+h@{instructions.\+h}}\index{instructions.\+h@{instructions.\+h}!ifnonnull@{ifnonnull}}\item[{\em 
ifnonnull\hypertarget{instructions_8h_a06fc87d81c62e9abb8790b6e5713c55babd6ddbe3310f6703b36fae4f5a26444f}{}\label{instructions_8h_a06fc87d81c62e9abb8790b6e5713c55babd6ddbe3310f6703b36fae4f5a26444f}
}]\index{ifnull@{ifnull}!instructions.\+h@{instructions.\+h}}\index{instructions.\+h@{instructions.\+h}!ifnull@{ifnull}}\item[{\em 
ifnull\hypertarget{instructions_8h_a06fc87d81c62e9abb8790b6e5713c55badd6d42007d139025320be3763128aff0}{}\label{instructions_8h_a06fc87d81c62e9abb8790b6e5713c55badd6d42007d139025320be3763128aff0}
}]\index{aload@{aload}!instructions.\+h@{instructions.\+h}}\index{instructions.\+h@{instructions.\+h}!aload@{aload}}\item[{\em 
aload\hypertarget{instructions_8h_a06fc87d81c62e9abb8790b6e5713c55ba083cba804dff6d007aae654e5b9ef655}{}\label{instructions_8h_a06fc87d81c62e9abb8790b6e5713c55ba083cba804dff6d007aae654e5b9ef655}
}]\index{aload\+\_\+0@{aload\+\_\+0}!instructions.\+h@{instructions.\+h}}\index{instructions.\+h@{instructions.\+h}!aload\+\_\+0@{aload\+\_\+0}}\item[{\em 
aload\+\_\+0\hypertarget{instructions_8h_a06fc87d81c62e9abb8790b6e5713c55ba73a8344343fd12fb6074b6c8d7564fb1}{}\label{instructions_8h_a06fc87d81c62e9abb8790b6e5713c55ba73a8344343fd12fb6074b6c8d7564fb1}
}]\index{aload\+\_\+1@{aload\+\_\+1}!instructions.\+h@{instructions.\+h}}\index{instructions.\+h@{instructions.\+h}!aload\+\_\+1@{aload\+\_\+1}}\item[{\em 
aload\+\_\+1\hypertarget{instructions_8h_a06fc87d81c62e9abb8790b6e5713c55bac3a421ab835d4a2b59f8892f79374284}{}\label{instructions_8h_a06fc87d81c62e9abb8790b6e5713c55bac3a421ab835d4a2b59f8892f79374284}
}]\index{aload\+\_\+2@{aload\+\_\+2}!instructions.\+h@{instructions.\+h}}\index{instructions.\+h@{instructions.\+h}!aload\+\_\+2@{aload\+\_\+2}}\item[{\em 
aload\+\_\+2\hypertarget{instructions_8h_a06fc87d81c62e9abb8790b6e5713c55bace3ae920ba39fd1ca14c32927b96bef9}{}\label{instructions_8h_a06fc87d81c62e9abb8790b6e5713c55bace3ae920ba39fd1ca14c32927b96bef9}
}]\index{aload\+\_\+3@{aload\+\_\+3}!instructions.\+h@{instructions.\+h}}\index{instructions.\+h@{instructions.\+h}!aload\+\_\+3@{aload\+\_\+3}}\item[{\em 
aload\+\_\+3\hypertarget{instructions_8h_a06fc87d81c62e9abb8790b6e5713c55ba2e3b02b418d4895ba8a60e911a029eef}{}\label{instructions_8h_a06fc87d81c62e9abb8790b6e5713c55ba2e3b02b418d4895ba8a60e911a029eef}
}]\index{areturn@{areturn}!instructions.\+h@{instructions.\+h}}\index{instructions.\+h@{instructions.\+h}!areturn@{areturn}}\item[{\em 
areturn\hypertarget{instructions_8h_a06fc87d81c62e9abb8790b6e5713c55badc18648a3db2995e563636a41ad36340}{}\label{instructions_8h_a06fc87d81c62e9abb8790b6e5713c55badc18648a3db2995e563636a41ad36340}
}]\index{return\+\_\+original@{return\+\_\+original}!instructions.\+h@{instructions.\+h}}\index{instructions.\+h@{instructions.\+h}!return\+\_\+original@{return\+\_\+original}}\item[{\em 
return\+\_\+original\hypertarget{instructions_8h_a06fc87d81c62e9abb8790b6e5713c55ba9a97fb20f5ff36205d94c72df2e62dde}{}\label{instructions_8h_a06fc87d81c62e9abb8790b6e5713c55ba9a97fb20f5ff36205d94c72df2e62dde}
}]\index{tableswitch@{tableswitch}!instructions.\+h@{instructions.\+h}}\index{instructions.\+h@{instructions.\+h}!tableswitch@{tableswitch}}\item[{\em 
tableswitch\hypertarget{instructions_8h_a06fc87d81c62e9abb8790b6e5713c55bae7b0ecf96d2bf1ef455ba9488697c85a}{}\label{instructions_8h_a06fc87d81c62e9abb8790b6e5713c55bae7b0ecf96d2bf1ef455ba9488697c85a}
}]\index{lookupswitch@{lookupswitch}!instructions.\+h@{instructions.\+h}}\index{instructions.\+h@{instructions.\+h}!lookupswitch@{lookupswitch}}\item[{\em 
lookupswitch\hypertarget{instructions_8h_a06fc87d81c62e9abb8790b6e5713c55bacc321be87baf3cf4b6e0d4b569776156}{}\label{instructions_8h_a06fc87d81c62e9abb8790b6e5713c55bacc321be87baf3cf4b6e0d4b569776156}
}]\index{wide@{wide}!instructions.\+h@{instructions.\+h}}\index{instructions.\+h@{instructions.\+h}!wide@{wide}}\item[{\em 
wide\hypertarget{instructions_8h_a06fc87d81c62e9abb8790b6e5713c55bacf3cc7b9218abdf037d624446b916f67}{}\label{instructions_8h_a06fc87d81c62e9abb8790b6e5713c55bacf3cc7b9218abdf037d624446b916f67}
}]\index{iinc@{iinc}!instructions.\+h@{instructions.\+h}}\index{instructions.\+h@{instructions.\+h}!iinc@{iinc}}\item[{\em 
iinc\hypertarget{instructions_8h_a06fc87d81c62e9abb8790b6e5713c55ba947df06f627174c299830f76cf19a3c7}{}\label{instructions_8h_a06fc87d81c62e9abb8790b6e5713c55ba947df06f627174c299830f76cf19a3c7}
}]\index{bipush@{bipush}!instructions.\+h@{instructions.\+h}}\index{instructions.\+h@{instructions.\+h}!bipush@{bipush}}\item[{\em 
bipush\hypertarget{instructions_8h_a06fc87d81c62e9abb8790b6e5713c55bafd6c7d5aac2787536813938ae70e9f73}{}\label{instructions_8h_a06fc87d81c62e9abb8790b6e5713c55bafd6c7d5aac2787536813938ae70e9f73}
}]\end{description}
\end{Desc}


\subsection{Function Documentation}
\index{instructions.\+h@{instructions.\+h}!initialize\+\_\+op\+\_\+codes@{initialize\+\_\+op\+\_\+codes}}
\index{initialize\+\_\+op\+\_\+codes@{initialize\+\_\+op\+\_\+codes}!instructions.\+h@{instructions.\+h}}
\subsubsection[{\texorpdfstring{initialize\+\_\+op\+\_\+codes()}{initialize_op_codes()}}]{\setlength{\rightskip}{0pt plus 5cm}void initialize\+\_\+op\+\_\+codes (
\begin{DoxyParamCaption}
{}
\end{DoxyParamCaption}
)}\hypertarget{instructions_8h_afc6e90df89f862010ce7c75d0663ea08}{}\label{instructions_8h_afc6e90df89f862010ce7c75d0663ea08}


Here is the caller graph for this function\+:
\nopagebreak
\begin{figure}[H]
\begin{center}
\leavevmode
\includegraphics[width=253pt]{instructions_8h_afc6e90df89f862010ce7c75d0663ea08_icgraph}
\end{center}
\end{figure}




\subsection{Variable Documentation}
\index{instructions.\+h@{instructions.\+h}!instructions@{instructions}}
\index{instructions@{instructions}!instructions.\+h@{instructions.\+h}}
\subsubsection[{\texorpdfstring{instructions}{instructions}}]{\setlength{\rightskip}{0pt plus 5cm}enum \{ ... \}   instructions}\hypertarget{instructions_8h_ad80be7537d54389cd2647bb57b4cbf35}{}\label{instructions_8h_ad80be7537d54389cd2647bb57b4cbf35}


Enum com informações dos opcodes da \hyperlink{structJVM}{J\+VM}. 

\index{instructions.\+h@{instructions.\+h}!op\+\_\+codes\+\_\+array@{op\+\_\+codes\+\_\+array}}
\index{op\+\_\+codes\+\_\+array@{op\+\_\+codes\+\_\+array}!instructions.\+h@{instructions.\+h}}
\subsubsection[{\texorpdfstring{op\+\_\+codes\+\_\+array}{op_codes_array}}]{\setlength{\rightskip}{0pt plus 5cm}{\bf op\+\_\+code} op\+\_\+codes\+\_\+array\mbox{[}300\mbox{]}}\hypertarget{instructions_8h_a7037db4717b2292017d30ccec8c29b64}{}\label{instructions_8h_a7037db4717b2292017d30ccec8c29b64}
